LICENSE
README.md
lr_schedules/__init__.py
lr_schedules/interp.py
lr_schedules/linear_scheduler.py
lr_schedules-0.0.2.dist-info/LICENSE
lr_schedules-0.0.2.dist-info/METADATA
lr_schedules-0.0.2.dist-info/WHEEL
lr_schedules-0.0.2.dist-info/RECORD
