Metadata-Version: 2.1
Name: lr_schedules
Version: 0.0.2
Summary: Learning rate schedulers, for libraries like PyTorch
Home-page: https://github.com/sradc/lr_schedules
License: Apache-2.0
Author: sradc
Author-email: sidneyradcliffe@sky.com
Requires-Python: >=3.9
Classifier: License :: OSI Approved :: Apache Software License
Classifier: Programming Language :: Python :: 3
Classifier: Programming Language :: Python :: 3.9
Classifier: Programming Language :: Python :: 3.10
Classifier: Programming Language :: Python :: 3.11
Project-URL: Repository, https://github.com/sradc/lr_schedules
